app/__init__.py
app/config.py
app/monitor.py
pynitor-0.2.0.dist-info/METADATA
pynitor-0.2.0.dist-info/WHEEL
pynitor-0.2.0.dist-info/entry_points.txt
pynitor-0.2.0.dist-info/top_level.txt
pynitor-0.2.0.dist-info/RECORD
