Metadata-Version: 2.1
Name: pynitor
Version: 0.2.0
Summary: A simple application to monitor the health of multiple applications and send notifications to Discord.
Home-page: https://github.com/na0495/pynitor
Author: Saad Mrabet
Author-email: saad.mrabet@kubicbits.com
Classifier: Programming Language :: Python :: 3
Classifier: License :: OSI Approved :: MIT License
Classifier: Operating System :: OS Independent
Requires-Python: >=3.6
Requires-Dist: requests
